{
  "_class": "group",
  "do_objectID": "ED64B6ED-E3B1-4582-A675-ED3048565474",
  "exportOptions": {
    "_class": "exportOptions",
    "exportFormats": [
    ],
    "includedLayerIds": [
    ],
    "layerOptions": 0,
    "shouldTrim": false
  },
  "frame": {
    "_class": "rect",
    "constrainProportions": false,
    "height": 45,
    "width": 72,
    "x": 0,
    "y": 0
  },
  "hasClickThrough": false,
  "isFlippedHorizontal": false,
  "isFlippedVertical": false,
  "isLocked": false,
  "isVisible": true,
  "layerListExpandedType": 0,
  "layers": [
    {
      "class": "group",
      "id": "978519EB-93D8-4712-9ED2-0AB83B5507E2"
    },
    {
      "class": "group",
      "id": "32EF0442-C550-49CE-A7C2-5B3938CFA401"
    },
    {
      "class": "group",
      "id": "7BA8F69E-4409-4AE5-9ECB-E4FD933E6D11"
    },
    {
      "class": "group",
      "id": "E53ED635-DD7E-495D-984E-F476E0A67735"
    }
  ],
  "name": "main",
  "nameIsFixed": false,
  "resizingConstraint": 63,
  "resizingType": 0,
  "rotation": 0,
  "shouldBreakMaskChain": false,
  "style": {
    "_class": "style",
    "blur": {
      "_class": "blur",
      "center": "{0.5, 0.5}",
      "isEnabled": false,
      "motionAngle": 0,
      "radius": 2.271293375394322,
      "type": 0
    },
    "endDecorationType": 0,
    "miterLimit": 10,
    "startDecorationType": 0
  },
  "userInfo": {
    "com.animaapp.stc-sketch-plugin": {
      "kModelPropertiesKey": {
      }
    }
  }
}